coolpyterm/__init__.py
coolpyterm/backend_factory.py
coolpyterm/checkogl.py
coolpyterm/connection_manager.py
coolpyterm/cpt.py
coolpyterm/key_handler_ssh.py
coolpyterm/log_handler.py
coolpyterm/opengl_grid_widget.py
coolpyterm/retro_theme_manager.py
coolpyterm/settings_manager.py
coolpyterm/ssh_backend.py
coolpyterm/sshshellreader.py
coolpyterm/winptyshellreader.py
coolpyterm-0.2.1.dist-info/licenses/LICENSE
coolpyterm-0.2.1.dist-info/METADATA
coolpyterm-0.2.1.dist-info/WHEEL
coolpyterm-0.2.1.dist-info/entry_points.txt
coolpyterm-0.2.1.dist-info/top_level.txt
coolpyterm-0.2.1.dist-info/RECORD
