Metadata-Version: 2.4
Name: coolpyterm
Version: 0.2.1
Summary: A hardware-accelerated SSH terminal emulator with authentic retro CRT effects, inspired by the Cool Retro Terminal project
Home-page: https://github.com/scottpeterman/coolpyterm
Author: Scott Peterman
Author-email: scottpeterman@gmail.com
Classifier: Development Status :: 4 - Beta
Classifier: Environment :: X11 Applications :: Qt
Classifier: Intended Audience :: Developers
Classifier: Intended Audience :: System Administrators
Classifier: License :: OSI Approved :: GNU General Public License v3 or later (GPLv3+)
Classifier: Operating System :: OS Independent
Classifier: Programming Language :: Python :: 3
Classifier: Programming Language :: Python :: 3.10
Classifier: Programming Language :: Python :: 3.11
Classifier: Programming Language :: Python :: 3.12
Classifier: Topic :: Internet
Classifier: Topic :: System :: Networking
Classifier: Topic :: Terminals
Classifier: Topic :: Utilities
Requires-Python: >=3.10
License-File: LICENSE
Requires-Dist: bcrypt>=4.3.0
Requires-Dist: cffi>=1.17.1
Requires-Dist: cryptography>=45.0.5
Requires-Dist: numpy>=2.3.1
Requires-Dist: paramiko>=3.5.1
Requires-Dist: pycparser>=2.22
Requires-Dist: PyNaCl>=1.5.0
Requires-Dist: PyOpenGL>=3.1.9
Requires-Dist: PyQt6>=6.9.1
Requires-Dist: PyQt6-Qt6>=6.9.1
Requires-Dist: PyQt6_sip>=13.10.2
Requires-Dist: pyte>=0.8.2
Requires-Dist: wcwidth>=0.2.13
Requires-Dist: pywinpty>=2.0.15
Provides-Extra: dev
Dynamic: author
Dynamic: author-email
Dynamic: classifier
Dynamic: description
Dynamic: description-content-type
Dynamic: home-page
Dynamic: license-file
Dynamic: provides-extra
Dynamic: requires-dist
Dynamic: requires-python
Dynamic: summary
